MANIFEST.in
README.md
setup.py
max_span/__init__.py
max_span.egg-info/PKG-INFO
max_span.egg-info/SOURCES.txt
max_span.egg-info/dependency_links.txt
max_span.egg-info/entry_points.txt
max_span.egg-info/requires.txt
max_span.egg-info/top_level.txt