Metadata-Version: 2.1
Name: max-span
Version: 0.0.0
Summary: Max Span
Home-page: https://github.com/blester125/max_span
Author: blester125
Author-email: blester125@gmail.com
License: MIT
Download-URL: https://github.com/blester125/max_span/archive/0.0.0.tar.gz
Platform: UNKNOWN
Classifier: Topic :: Scientific/Engineering
Classifier: Intended Audience :: Developers
Classifier: Development Status :: 3 - Alpha
Classifier: Programming Language :: Python :: 3 :: Only
Classifier: Intended Audience :: Science/Research
Classifier: Environment :: Console
Classifier: Natural Language :: English
Classifier: License :: OSI Approved :: MIT License
Requires-Python: >=3.6
Provides-Extra: test
